historical_scam_summary/__init__.py
historical_scam_summary/main.py
historical_scam_summary/prompts.py
historical_scam_summary-2025.12.21102119.dist-info/METADATA
historical_scam_summary-2025.12.21102119.dist-info/WHEEL
historical_scam_summary-2025.12.21102119.dist-info/top_level.txt
historical_scam_summary-2025.12.21102119.dist-info/RECORD
