Metadata-Version: 2.4
Name: historical-scam-summary
Version: 2025.12.21102119
Summary: This package solves the problem of extracting structured, domain-specific insights from unstructured text inputs—like historical articles, research papers, or summaries—without requiring manual parsin
Author-email: historical-scam-summary <hi@eugene.plus>
License: MIT
Project-URL: Homepage, https://github.com/chigwell/historical-scam-summary
Requires-Python: >=3.9
Requires-Dist: langchain-llm7>=0.0.0
Requires-Dist: llmatch-messages>=0.0.0
Requires-Dist: langchain-core>=0.3.0
